pygooglecloud/__init__.py
pygooglecloud/configs.py
pygooglecloud/main.py
pygooglecloud/static.py
pygooglecloud-0.0.3.dist-info/LICENSE
pygooglecloud-0.0.3.dist-info/METADATA
pygooglecloud-0.0.3.dist-info/WHEEL
pygooglecloud-0.0.3.dist-info/entry_points.txt
pygooglecloud-0.0.3.dist-info/top_level.txt
pygooglecloud-0.0.3.dist-info/RECORD
