Metadata-Version: 2.1
Name: pygooglecloud
Version: 0.0.3
Summary: pygooglecloud helps you with command line interaction with gcp
Home-page: https://veltzer.github.io/pygooglecloud
Download-URL: https://github.com/veltzer/pygooglecloud
Author: Mark Veltzer
Author-email: mark.veltzer@gmail.com
Maintainer: Mark Veltzer
Maintainer-email: mark.veltzer@gmail.com
License: MIT
Keywords: gcp,gae,python,shell,utilities
Platform: python3
Classifier: Development Status :: 4 - Beta
Classifier: Environment :: Console
Classifier: Operating System :: OS Independent
Classifier: Programming Language :: Python
Classifier: Programming Language :: Python :: 3
Classifier: Programming Language :: Python :: 3 :: Only
Classifier: Programming Language :: Python :: 3.11
Classifier: Topic :: Utilities
Classifier: License :: OSI Approved :: MIT License
License-File: LICENSE
Requires-Dist: pylogconf
Requires-Dist: pytconf
Requires-Dist: google-auth
